{"is_source_file": true, "format": "Python", "description": "This file defines a FastAPI backend API for the Task Organizer Pro application, implementing endpoints for health checks, authentication (signup, login), and CRUD operations for tasks with filtering and sorting options. It uses dependency injection and modules for database interaction, security, and data models.", "external_files": ["src.api.deps", "src.core.config", "src.core.security", "src.db.migrate", "src.models.auth", "src.models.tasks", "src.repos.tasks", "src.repos.users"], "external_methods": ["get_conn", "get_current_user", "get_settings", "create_access_token", "run_migrations"], "published": ["app", "health_check", "auth_docs", "signup", "login", "list_tasks", "create_task", "get_task", "update_task", "delete_task"], "classes": [], "methods": [{"name": "health_check()", "description": "Health check endpoint returning service status.", "scope": "", "scopeKind": ""}, {"name": "auth_docs()", "description": "Returns instructions for using JWT authentication.", "scope": "", "scopeKind": ""}, {"name": "signup(payload: SignUpRequest, conn=Depends(get_conn))", "description": "Registers a new user, ensuring email uniqueness.", "scope": "", "scopeKind": ""}, {"name": "login(payload: LoginRequest, conn=Depends(get_conn))", "description": "Authenticates user and issues a JWT token.", "scope": "", "scopeKind": ""}, {"name": "list_tasks( response: Response, q: Optional[str] = Query(None, description=\"Full-text search query (title+description).\"), status_: Optional[str] = Query(None, alias=\"status\", description=\"Filter by status: todo|in_progress|done.\"), priority: Optional[str] = Query(None, description=\"Filter by priority: low|medium|high.\"), due_from: Optional[date] = Query(None, description=\"Due date >= (YYYY-MM-DD).\"), due_to: Optional[date] = Query(None, description=\"Due date <= (YYYY-MM-DD).\"), sort: str = Query(\"created_at\", description=\"Sort field: created_at|updated_at|due_date|priority|status|title.\"), order: str = Query(\"desc\", description=\"Sort order: asc|desc.\"), limit: int = Query(50, ge=1, le=200, description=\"Page size.\"), offset: int = Query(0, ge=0, description=\"Offset for pagination.\"), user=Depends(get_current_user), conn=Depends(get_conn), )", "description": "Lists tasks for the current user with optional filters, sorting, and pagination.", "scope": "", "scopeKind": ""}, {"name": "create_task(payload: TaskCreateRequest, user=Depends(get_current_user), conn=Depends(get_conn))", "description": "Creates a new task for the authenticated user.", "scope": "", "scopeKind": ""}, {"name": "get_task(task_id: str, user=Depends(get_current_user), conn=Depends(get_conn))", "description": "Retrieves a specific task by ID for the current user.", "scope": "", "scopeKind": ""}, {"name": "update_task(task_id: str, payload: TaskUpdateRequest, user=Depends(get_current_user), conn=Depends(get_conn))", "description": "Updates fields of a specific task.", "scope": "", "scopeKind": ""}, {"name": "delete_task(task_id: str, user=Depends(get_current_user), conn=Depends(get_conn))", "description": "Deletes a specific task.", "scope": "", "scopeKind": ""}, {"name": "None _startup()", "scope": "", "scopeKind": "", "description": "unavailable"}], "calls": ["run_migrations", "get_settings", "create_access_token", "get_conn", "get_current_user", "UsersRepo.get_by_email", "UsersRepo.create", "UsersRepo.authenticate", "TasksRepo.list", "TasksRepo.create", "TasksRepo.get", "TasksRepo.update", "TasksRepo.delete"], "search-terms": ["FastAPI backend", "JWT auth", "task CRUD endpoints", "task filtering", "user signup", "task list", "task get by id", "task update", "task delete", "CORS middleware"], "state": 2, "file_id": 3, "knowledge_revision": 25, "git_revision": "e0551201f58975b3c74f93dba3ff28da63d92cb7", "revision_history": [{"9": "35b810ad925051597ccc95a4ecaffebd07b31d1f"}, {"25": "e0551201f58975b3c74f93dba3ff28da63d92cb7"}], "ctags": [{"_type": "tag", "name": "_startup", "path": "/home/kavia/workspace/code-generation/task-organizer-pro-244843-244859/task_management_backend/src/api/main.py", "pattern": "/^async def _startup() -> None:$/", "language": "Python", "typeref": "typename:None", "kind": "function", "signature": "()"}, {"_type": "tag", "name": "app", "path": "/home/kavia/workspace/code-generation/task-organizer-pro-244843-244859/task_management_backend/src/api/main.py", "pattern": "/^app = FastAPI($/", "language": "Python", "kind": "variable"}, {"_type": "tag", "name": "auth_docs", "path": "/home/kavia/workspace/code-generation/task-organizer-pro-244843-244859/task_management_backend/src/api/main.py", "pattern": "/^def auth_docs():$/", "language": "Python", "kind": "function", "signature": "()"}, {"_type": "tag", "name": "create_task", "path": "/home/kavia/workspace/code-generation/task-organizer-pro-244843-244859/task_management_backend/src/api/main.py", "pattern": "/^def create_task(payload: TaskCreateRequest, user=Depends(get_current_user), conn=Depends(get_con/", "language": "Python", "kind": "function", "signature": "(payload: TaskCreateRequest, user=Depends(get_current_user), conn=Depends(get_conn))"}, {"_type": "tag", "name": "delete_task", "path": "/home/kavia/workspace/code-generation/task-organizer-pro-244843-244859/task_management_backend/src/api/main.py", "pattern": "/^def delete_task(task_id: str, user=Depends(get_current_user), conn=Depends(get_conn)):$/", "language": "Python", "kind": "function", "signature": "(task_id: str, user=Depends(get_current_user), conn=Depends(get_conn))"}, {"_type": "tag", "name": "get_task", "path": "/home/kavia/workspace/code-generation/task-organizer-pro-244843-244859/task_management_backend/src/api/main.py", "pattern": "/^def get_task(task_id: str, user=Depends(get_current_user), conn=Depends(get_conn)):$/", "language": "Python", "kind": "function", "signature": "(task_id: str, user=Depends(get_current_user), conn=Depends(get_conn))"}, {"_type": "tag", "name": "health_check", "path": "/home/kavia/workspace/code-generation/task-organizer-pro-244843-244859/task_management_backend/src/api/main.py", "pattern": "/^def health_check():$/", "language": "Python", "kind": "function", "signature": "()"}, {"_type": "tag", "name": "list_tasks", "path": "/home/kavia/workspace/code-generation/task-organizer-pro-244843-244859/task_management_backend/src/api/main.py", "pattern": "/^def list_tasks($/", "language": "Python", "kind": "function", "signature": "( response: Response, q: Optional[str] = Query(None, description=\"Full-text search query (title+description).\"), status_: Optional[str] = Query(None, alias=\"status\", description=\"Filter by status: todo|in_progress|done.\"), priority: Optional[str] = Query(None, description=\"Filter by priority: low|medium|high.\"), due_from: Optional[date] = Query(None, description=\"Due date >= (YYYY-MM-DD).\"), due_to: Optional[date] = Query(None, description=\"Due date <= (YYYY-MM-DD).\"), sort: str = Query(\"created_at\", description=\"Sort field: created_at|updated_at|due_date|priority|status|title.\"), order: str = Query(\"desc\", description=\"Sort order: asc|desc.\"), limit: int = Query(50, ge=1, le=200, description=\"Page size.\"), offset: int = Query(0, ge=0, description=\"Offset for pagination.\"), user=Depends(get_current_user), conn=Depends(get_conn), )"}, {"_type": "tag", "name": "login", "path": "/home/kavia/workspace/code-generation/task-organizer-pro-244843-244859/task_management_backend/src/api/main.py", "pattern": "/^def login(payload: LoginRequest, conn=Depends(get_conn)):$/", "language": "Python", "kind": "function", "signature": "(payload: LoginRequest, conn=Depends(get_conn))"}, {"_type": "tag", "name": "openapi_tags", "path": "/home/kavia/workspace/code-generation/task-organizer-pro-244843-244859/task_management_backend/src/api/main.py", "pattern": "/^openapi_tags = [$/", "language": "Python", "kind": "variable"}, {"_type": "tag", "name": "settings", "path": "/home/kavia/workspace/code-generation/task-organizer-pro-244843-244859/task_management_backend/src/api/main.py", "pattern": "/^settings = get_settings()$/", "language": "Python", "kind": "variable"}, {"_type": "tag", "name": "signup", "path": "/home/kavia/workspace/code-generation/task-organizer-pro-244843-244859/task_management_backend/src/api/main.py", "pattern": "/^def signup(payload: SignUpRequest, conn=Depends(get_conn)):$/", "language": "Python", "kind": "function", "signature": "(payload: SignUpRequest, conn=Depends(get_conn))"}, {"_type": "tag", "name": "update_task", "path": "/home/kavia/workspace/code-generation/task-organizer-pro-244843-244859/task_management_backend/src/api/main.py", "pattern": "/^def update_task(task_id: str, payload: TaskUpdateRequest, user=Depends(get_current_user), conn=D/", "language": "Python", "kind": "function", "signature": "(task_id: str, payload: TaskUpdateRequest, user=Depends(get_current_user), conn=Depends(get_conn))"}], "hash": "1212cc4fa4aabadd4f2c428134ca2e4c", "format-version": 4, "code-base-name": "task_management_backend", "filename": "task_management_backend/src/api/main.py", "fields": [{"name": "app = FastAPI(", "scope": "", "scopeKind": "", "description": "unavailable"}, {"name": "openapi_tags = [", "scope": "", "scopeKind": "", "description": "unavailable"}, {"name": "settings = get_settings()", "scope": "", "scopeKind": "", "description": "unavailable"}]}